LICENSE
pyproject.toml
setup.cfg
setup.py
curated_transformers_addons/__init__.py
curated_transformers_addons.egg-info/PKG-INFO
curated_transformers_addons.egg-info/SOURCES.txt
curated_transformers_addons.egg-info/dependency_links.txt
curated_transformers_addons.egg-info/requires.txt
curated_transformers_addons.egg-info/top_level.txt
curated_transformers_addons.egg-info/zip-safe